MANIFEST.in
setup.py
dexy_filter_examples/__init__.py
dexy_filter_examples/__init__.pyc
dexy_filter_examples.egg-info/PKG-INFO
dexy_filter_examples.egg-info/SOURCES.txt
dexy_filter_examples.egg-info/dependency_links.txt
dexy_filter_examples.egg-info/requires.txt
dexy_filter_examples.egg-info/top_level.txt
dexy_filter_examples/abc-template/dexy.rst
dexy_filter_examples/abc-template/dexy.yaml
dexy_filter_examples/abc-template/jingle.abc
dexy_filter_examples/asciidoc-template/dexy.rst
dexy_filter_examples/asciidoc-template/dexy.yaml
dexy_filter_examples/asciidoc-template/example.adoc
dexy_filter_examples/asciidoctor-template/dexy.rst
dexy_filter_examples/asciidoctor-template/dexy.yaml
dexy_filter_examples/asciidoctor-template/example1.adoc
dexy_filter_examples/asciidoctor-template/example2.adoc
dexy_filter_examples/bash-template/dexy.rst
dexy_filter_examples/bash-template/dexy.yaml
dexy_filter_examples/bash-template/script.sh
dexy_filter_examples/bash-template/whereami.sh
dexy_filter_examples/cowsay-template/dexy.rst
dexy_filter_examples/cowsay-template/dexy.yaml
dexy_filter_examples/cowsay-template/hello.txt
dexy_filter_examples/cowsay-template/youthful.txt
dexy_filter_examples/ditaa-template/dexy.rst
dexy_filter_examples/ditaa-template/dexy.yaml
dexy_filter_examples/ditaa-template/diagram.txt
dexy_filter_examples/figlet-template/dexy.rst
dexy_filter_examples/figlet-template/dexy.yaml
dexy_filter_examples/figlet-template/figlet.txt
dexy_filter_examples/go-template/dexy.rst
dexy_filter_examples/go-template/dexy.yaml
dexy_filter_examples/go-template/hello.go
dexy_filter_examples/go-template/rand.go
dexy_filter_examples/go-template/silly_test.go
dexy_filter_examples/htmlsections-template/dexy.rst
dexy_filter_examples/htmlsections-template/dexy.yaml
dexy_filter_examples/htmlsections-template/docs.html
dexy_filter_examples/htmlsections-template/sections.html
dexy_filter_examples/idio-template/dexy.rst
dexy_filter_examples/idio-template/dexy.yaml
dexy_filter_examples/idio-template/example.c
dexy_filter_examples/idio-template/example.clj
dexy_filter_examples/idio-template/example.html
dexy_filter_examples/idio-template/example.py
dexy_filter_examples/idio-template/example.tex
